wies_library
