Metadata-Version: 2.1
Name: wies-library
Version: 0.0.3
Summary: This is a great library
Home-page: https://github.com/wieszheng/Cprint
Author: zhengduoduo
Author-email: 1512945835@qq.com
License: MIT
Keywords: python,windows,mac,linux
Platform: UNKNOWN
Classifier: Development Status :: 1 - Planning
Classifier: Intended Audience :: Developers
Classifier: Programming Language :: Python :: 3
Classifier: Operating System :: Unix
Classifier: Operating System :: MacOS :: MacOS X
Classifier: Operating System :: Microsoft :: Windows
